service/__init__.py
service/cli.py
service/launchctl.py
service/service.py
py_service-2.0.3.dist-info/LICENSE
py_service-2.0.3.dist-info/METADATA
py_service-2.0.3.dist-info/WHEEL
py_service-2.0.3.dist-info/entry_points.txt
py_service-2.0.3.dist-info/RECORD
